marctable/__init__.py
marctable/marc.json
marctable/marc.py
marctable/utils.py
marctable-0.6.0.dist-info/METADATA
marctable-0.6.0.dist-info/WHEEL
marctable-0.6.0.dist-info/entry_points.txt
marctable-0.6.0.dist-info/licenses/LICENSE
marctable-0.6.0.dist-info/RECORD
