Metadata-Version: 2.4
Name: marctable
Version: 0.6.0
Summary: Convert MARC to CSV and Parquet
Project-URL: Homepage, https://github.com/sul-dlss-labs/marctable
Author-email: Ed Summers <ehs@pobox.com>
License:                                  Apache License
License-File: LICENSE
Requires-Python: >=3.12
Requires-Dist: beautifulsoup4>=4.12.2
Requires-Dist: click>=8.1.7
Requires-Dist: pandas>=2.1.4
Requires-Dist: pyarrow>=14.0.2
Requires-Dist: pymarc>=5.1.0
Requires-Dist: requests>=2.31.0
